daypy/__init__.py
daypy/constant.py
daypy/plugins/__init__.py
daypy/plugins/array_support.py
daypy/plugins/dict_support.py
daypy/plugins/human.py
daypy/plugins/is_leap_year.py
daypy/plugins/to.py
daypy/plugins/zh_support.py
daypy/utils.py
daypy-0.2.3.dist-info/WHEEL
daypy-0.2.3.dist-info/METADATA
daypy-0.2.3.dist-info/RECORD
