Metadata-Version: 2.1
Name: daypy
Version: 0.2.3
Summary: 一个日期时间解析器
Home-page: https://github.com/mic1on/daypy
Keywords: 日期解析,年月日解析,日期时间
Author: miclon
Author-email: jcnd@163.com
Requires-Python: >=3.8,<4.0
Classifier: Programming Language :: Python :: 3
Classifier: Programming Language :: Python :: 3.8
Classifier: Programming Language :: Python :: 3.9
Classifier: Programming Language :: Python :: 3.10
Requires-Dist: arrow (>=1.2.2,<2.0.0)
